package/__init__.py
package/firstModule.py
dpp_token_api_lib-0.2.dist-info/LICENSE.md
dpp_token_api_lib-0.2.dist-info/METADATA
dpp_token_api_lib-0.2.dist-info/WHEEL
dpp_token_api_lib-0.2.dist-info/top_level.txt
dpp_token_api_lib-0.2.dist-info/RECORD
