Metadata-Version: 2.1
Name: dpp-token-api-lib
Version: 0.2
Summary: An example python package
Home-page: https://git.e-science.pl/kwazny_252716_dpp/kwazny252716_dpp_python_pip
Author: Karol Ważny
Author-email: kwazny_252716@e-science.pl
License: MIT
Platform: UNKNOWN
License-File: LICENSE.md
